joban/__init__.py
joban/topsis_101903552.py
Topsis_jobanvir_101903552-0.0.1.dist-info/METADATA
Topsis_jobanvir_101903552-0.0.1.dist-info/WHEEL
Topsis_jobanvir_101903552-0.0.1.dist-info/top_level.txt
Topsis_jobanvir_101903552-0.0.1.dist-info/RECORD
